{
	"configurations" : 
	[
		{
			"directories" : 
			[
				{
					"build" : ".",
					"jsonFile" : "directory-.-Debug-f5ebdc15457944623624.json",
					"minimumCMakeVersion" : 
					{
						"string" : "3.27"
					},
					"projectIndex" : 0,
					"source" : ".",
					"targetIndexes" : 
					[
						0,
						1,
						2
					]
				}
			],
			"name" : "Debug",
			"projects" : 
			[
				{
					"directoryIndexes" : 
					[
						0
					],
					"name" : "Exam",
					"targetIndexes" : 
					[
						0,
						1,
						2
					]
				}
			],
			"targets" : 
			[
				{
					"directoryIndex" : 0,
					"id" : "Exam::@6890427a1f51a3e7e1df",
					"jsonFile" : "target-Exam-Debug-56798c62c3645d6b2190.json",
					"name" : "Exam",
					"projectIndex" : 0
				},
				{
					"directoryIndex" : 0,
					"id" : "SymbolTableTests::@6890427a1f51a3e7e1df",
					"jsonFile" : "target-SymbolTableTests-Debug-f6bb3b32a97485111091.json",
					"name" : "SymbolTableTests",
					"projectIndex" : 0
				},
				{
					"directoryIndex" : 0,
					"id" : "VesselTests::@6890427a1f51a3e7e1df",
					"jsonFile" : "target-VesselTests-Debug-3b6485e899b9cc8e851a.json",
					"name" : "VesselTests",
					"projectIndex" : 0
				}
			]
		}
	],
	"kind" : "codemodel",
	"paths" : 
	{
		"build" : "/home/krogh/CLionProjects/cpp/Exam/cmake-build-debug",
		"source" : "/home/krogh/CLionProjects/cpp/Exam"
	},
	"version" : 
	{
		"major" : 2,
		"minor" : 6
	}
}
